docs/__init__.py
docs/conf.py
pyabsa/__init__.py
pyabsa/augmentation/__init__.py
pyabsa/augmentation/aug_utils.py
pyabsa/augmentation/apc_augment/__init__.py
pyabsa/augmentation/apc_augment/apc_augment.py
pyabsa/augmentation/text_augment/__init__.py
pyabsa/augmentation/text_augment/tc_augment.py
pyabsa/framework/__init__.py
pyabsa/framework/checkpoint_class/__init__.py
pyabsa/framework/checkpoint_class/checkpoint_template.py
pyabsa/framework/checkpoint_class/checkpoint_utils.py
pyabsa/framework/configuration_class/__init__.py
pyabsa/framework/configuration_class/config_verification.py
pyabsa/framework/configuration_class/configuration_template.py
pyabsa/framework/dataset_class/__init__.py
pyabsa/framework/dataset_class/dataset_dict_class.py
pyabsa/framework/dataset_class/dataset_template.py
pyabsa/framework/dataset_class/inference_dataset_class.py
pyabsa/framework/flag_class/__init__.py
pyabsa/framework/flag_class/flag_template.py
pyabsa/framework/instructor_class/__init__.py
pyabsa/framework/instructor_class/instructor_template.py
pyabsa/framework/prediction_class/__init__.py
pyabsa/framework/prediction_class/predictor_template.py
pyabsa/framework/predictor_class/__init__.py
pyabsa/framework/predictor_class/predictor_template.py
pyabsa/framework/sampler_class/__init__.py
pyabsa/framework/sampler_class/imblanced_sampler.py
pyabsa/framework/tokenizer_class/__init__.py
pyabsa/framework/tokenizer_class/tokenizer_class.py
pyabsa/framework/trainer_class/__init__.py
pyabsa/framework/trainer_class/trainer_template.py
pyabsa/networks/__init__.py
pyabsa/networks/attention.py
pyabsa/networks/bert_mean_pooler.py
pyabsa/networks/dynamic_rnn.py
pyabsa/networks/lcf_pooler.py
pyabsa/networks/lsa.py
pyabsa/networks/point_wise_feed_forward.py
pyabsa/networks/sa_encoder.py
pyabsa/networks/squeeze_embedding.py
pyabsa/networks/losses/ClassImblanceCE.py
pyabsa/networks/losses/FocalLoss.py
pyabsa/networks/losses/LDAMLoss.py
pyabsa/networks/losses/MAELoss.py
pyabsa-2.4.3.dist-info/licenses/LICENSE
pyabsa-2.4.3.dist-info/METADATA
pyabsa-2.4.3.dist-info/WHEEL
pyabsa-2.4.3.dist-info/top_level.txt
pyabsa-2.4.3.dist-info/RECORD
