Metadata-Version: 2.4
Name: pyabsa
Version: 2.4.3
Summary: This tool provides the state-of-the-art models for aspect term extraction (ATE), aspect polarity classification (APC), and text classification (TC).
Home-page: https://github.com/yangheng95/PyABSA
Author: Yang, Heng
Author-email: hy345@exeter.ac.uk
License: MIT
Classifier: License :: OSI Approved :: MIT License
Classifier: Programming Language :: Python :: 3.10
Classifier: Operating System :: OS Independent
Classifier: Topic :: Scientific/Engineering :: Artificial Intelligence
Classifier: Topic :: Software Development :: Libraries :: Python Modules
Requires-Python: <3.11, >=3.10
License-File: LICENSE
Requires-Dist: findfile>=2.0.0
Requires-Dist: autocuda>=0.16
Requires-Dist: metric-visualizer>=0.9.6
Requires-Dist: boostaug>=2.3.5
Requires-Dist: spacy
Requires-Dist: networkx
Requires-Dist: seqeval
Requires-Dist: update-checker
Requires-Dist: typing_extensions
Requires-Dist: tqdm
Requires-Dist: pytorch_warmup
Requires-Dist: termcolor
Requires-Dist: gitpython
Requires-Dist: transformers<4.30.0
Requires-Dist: torch>=1.0.0
Requires-Dist: pandas
Requires-Dist: sentencepiece
Provides-Extra: docs
Requires-Dist: recommonmark; extra == "docs"
Requires-Dist: nbsphinx; extra == "docs"
Requires-Dist: sphinx-autobuild; extra == "docs"
Requires-Dist: sphinx-rtd-theme; extra == "docs"
Requires-Dist: sphinx-markdown-tables; extra == "docs"
Requires-Dist: sphinx-copybutton; extra == "docs"
Requires-Dist: piccolo_theme; extra == "docs"
Provides-Extra: test
Requires-Dist: docformatter; extra == "test"
Requires-Dist: isort; extra == "test"
Requires-Dist: flake8; extra == "test"
Requires-Dist: pytest; extra == "test"
Requires-Dist: pytest-xdist; extra == "test"
Provides-Extra: deploy
Requires-Dist: twine; extra == "deploy"
Requires-Dist: wheel; extra == "deploy"
Requires-Dist: setuptools; extra == "deploy"
Requires-Dist: gradio; extra == "deploy"
Provides-Extra: dev
Requires-Dist: recommonmark; extra == "dev"
Requires-Dist: nbsphinx; extra == "dev"
Requires-Dist: sphinx-autobuild; extra == "dev"
Requires-Dist: sphinx-rtd-theme; extra == "dev"
Requires-Dist: sphinx-markdown-tables; extra == "dev"
Requires-Dist: sphinx-copybutton; extra == "dev"
Requires-Dist: piccolo_theme; extra == "dev"
Requires-Dist: docformatter; extra == "dev"
Requires-Dist: isort; extra == "dev"
Requires-Dist: flake8; extra == "dev"
Requires-Dist: pytest; extra == "dev"
Requires-Dist: pytest-xdist; extra == "dev"
Requires-Dist: twine; extra == "dev"
Requires-Dist: wheel; extra == "dev"
Requires-Dist: setuptools; extra == "dev"
Requires-Dist: gradio; extra == "dev"
Dynamic: author
Dynamic: author-email
Dynamic: classifier
Dynamic: description
Dynamic: description-content-type
Dynamic: home-page
Dynamic: license
Dynamic: license-file
Dynamic: provides-extra
Dynamic: requires-dist
Dynamic: requires-python
Dynamic: summary
